library_sun3/__init__.py
library_sun3/store_lib.py
library_sun3/table.py
library_sun3-1.0.0.dist-info/LICENSE
library_sun3-1.0.0.dist-info/METADATA
library_sun3-1.0.0.dist-info/WHEEL
library_sun3-1.0.0.dist-info/top_level.txt
library_sun3-1.0.0.dist-info/RECORD
